{
    "version": "1.0.2",
    "architecture": {
        "32bit": {
            "url": "https://github.com/stuarthicks/mrd/releases/download/v1.0.2/mrd_Windows_i386.zip",
            "bin": [
                "mrd.exe"
            ],
            "hash": "6b7721adc715333cef6ca79091cccc6ebc866bb9ca1c7cabc0ecc2fd9ea62f4b"
        },
        "64bit": {
            "url": "https://github.com/stuarthicks/mrd/releases/download/v1.0.2/mrd_Windows_x86_64.zip",
            "bin": [
                "mrd.exe"
            ],
            "hash": "517bd5e5e66311c2b7442ff4a8ccec700d2f55dedd0b05f3131da439a7dfe954"
        },
        "arm64": {
            "url": "https://github.com/stuarthicks/mrd/releases/download/v1.0.2/mrd_Windows_arm64.zip",
            "bin": [
                "mrd.exe"
            ],
            "hash": "fc0b00a4b9e5c925695d1d61989cf2957d928e61fb09c1072998879321e39405"
        }
    },
    "homepage": "https://github.com/stuarthicks/mrd",
    "license": "MIT",
    "description": "Decodes the primordial soup of video DRM headers"
}